action_throttle/__init__.py
action_throttle/admin.py
action_throttle/apps.py
action_throttle/middleware.py
action_throttle/models.py
action_throttle/rest.py
action_throttle/tests.py
action_throttle/throttle.py
action_throttle/throttle_settings.py
action_throttle/urls.py
action_throttle/utils.py
action_throttle/views.py
django_action_throttle-0.0.4.dist-info/LICENCE
django_action_throttle-0.0.4.dist-info/METADATA
django_action_throttle-0.0.4.dist-info/WHEEL
django_action_throttle-0.0.4.dist-info/top_level.txt
django_action_throttle-0.0.4.dist-info/RECORD
